LICENSE.txt
MANIFEST.in
README.md
setup.py
scripts/speed_shoot
scripts/yahi_all_in_one_maker
yahi/__init__.py
yahi/data.js
yahi/field.py
yahi/fixed_size_lookup.py
yahi/template.py
yahi/test_yahi.py
yahi.egg-info/PKG-INFO
yahi.egg-info/SOURCES.txt
yahi.egg-info/dependency_links.txt
yahi.egg-info/requires.txt
yahi.egg-info/top_level.txt