Metadata-Version: 2.1
Name: yahi
Version: 0.2.9
Summary: Versatile log parser
Home-page: https://github.com/jul/yahi
Author: Julien Tayon, Stephane Bard
Author-email: julien@tayon.net
License: PYTHON SOFTWARE FOUNDATION LICENSE VERSION 2
Keywords: log,parsing
Classifier: License :: OSI Approved :: Python Software Foundation License
Classifier: Operating System :: MacOS :: MacOS X
Classifier: Operating System :: Microsoft :: Windows
Classifier: Operating System :: POSIX
Classifier: Programming Language :: Python
License-File: LICENSE.txt
Requires-Dist: archery>=0.1
Requires-Dist: pygeoip
Requires-Dist: httpagentparser
Requires-Dist: repoze.lru>=0.6
